txportal/__init__.py
txportal/client.py
txportal/packet/__init__.py
txportal/packet/cmcc.py
txportal/packet/huawei.py
txportal/packet/pktutils.py
txportal/simulator/__init__.py
txportal/simulator/choosereactor.py
txportal/simulator/portald.py
txportal/simulator/simpp.py
txportal/simulator/handlers/__init__.py
txportal/simulator/handlers/auth_handler.py
txportal/simulator/handlers/base_handler.py
txportal/simulator/handlers/chellenge_handler.py
txportal/simulator/handlers/logout_handler.py
txportal/simulator/handlers/reqinfo_handler.py
txportal-0.0.5.data/scripts/tpsim
txportal-0.0.5.dist-info/DESCRIPTION.rst
txportal-0.0.5.dist-info/METADATA
txportal-0.0.5.dist-info/RECORD
txportal-0.0.5.dist-info/WHEEL
txportal-0.0.5.dist-info/eager_resources.txt
txportal-0.0.5.dist-info/metadata.json
txportal-0.0.5.dist-info/top_level.txt
txportal-0.0.5.dist-info/zip-safe
