Metadata-Version: 2.0
Name: txportal
Version: 0.0.5
Summary: Portal tools
Home-page: https://github.com/talkincode/txportal
Author: jamiesun
Author-email: jamiesun.net@gmail.com
License: MIT
Keywords: portal,cmcc,huawei,h3c,toughwlan
Platform: UNKNOWN
Classifier: Development Status :: 6 - Mature
Classifier: Intended Audience :: Developers
Classifier: Programming Language :: Python :: 2.6
Classifier: Programming Language :: Python :: 2.7
Classifier: Topic :: Software Development :: Libraries :: Python Modules
Requires-Dist: Twisted (>=15.0.0)
Requires-Dist: msgpack-python
Requires-Dist: txzmq
